gre.py
grefornoobs-1.1.2.dist-info/LICENSE
grefornoobs-1.1.2.dist-info/METADATA
grefornoobs-1.1.2.dist-info/WHEEL
grefornoobs-1.1.2.dist-info/top_level.txt
grefornoobs-1.1.2.dist-info/RECORD
