Metadata-Version: 2.1
Name: grefornoobs
Version: 1.1.2
Summary: Your python GRE preparation tool
Home-page: https://github.com/abdussamiakanda/grefornoobs
Author: Md. Abdus Sami Akanda
Author-email: abdussamiakanda@gmail.com
License: MIT
Platform: UNKNOWN
Classifier: License :: OSI Approved :: MIT License
Classifier: Programming Language :: Python :: 3.8
Classifier: Programming Language :: Python :: 3.9
